setup.py
oneDpack/__init__.py
oneDpack/oneDpacking.py
oneDpack/oneDpackingCG.py
oneDpack.egg-info/PKG-INFO
oneDpack.egg-info/SOURCES.txt
oneDpack.egg-info/dependency_links.txt
oneDpack.egg-info/requires.txt
oneDpack.egg-info/top_level.txt